pyseoa/__init__.py
pyseoa/analyzer.py
pyseoa/cli.py
pyseoa/crawler.py
pyseoa/smart_batch_analyzer.py
pyseoa/exports/__init__.py
pyseoa/exports/base_exporter.py
pyseoa/exports/csv_exporter.py
pyseoa/exports/exporter_factory.py
pyseoa/exports/fancy_html_exporter.py
pyseoa/exports/html_exporter.py
pyseoa/exports/json_exporter.py
pyseoa/exports/markdown_exporter.py
pyseoa/exports/pdf_exporter.py
pyseoa/exports/terminal_exporter.py
pyseoa-0.2.3.post1.dist-info/licenses/LICENSE
pyseoa-0.2.3.post1.dist-info/METADATA
pyseoa-0.2.3.post1.dist-info/WHEEL
pyseoa-0.2.3.post1.dist-info/entry_points.txt
pyseoa-0.2.3.post1.dist-info/top_level.txt
pyseoa-0.2.3.post1.dist-info/RECORD
