Metadata-Version: 2.4
Name: pyseoa
Version: 0.2.3.post1
Summary: A seo analysis tool library written in python, with CLI support.
Home-page: https://github.com/sempre76/pyseoa
Author: Mario Semper
Author-email: mario.semper@masem.at
License: MIT
Classifier: Programming Language :: Python :: 3
Classifier: License :: OSI Approved :: MIT License
Classifier: Operating System :: OS Independent
Classifier: Intended Audience :: Developers
Classifier: Topic :: Internet :: WWW/HTTP :: Site Management
Requires-Python: >=3.7
License-File: LICENSE
Requires-Dist: requests
Requires-Dist: beautifulsoup4
Requires-Dist: tqdm
Dynamic: license-file
